{
  "name": "Receiver",
  "basegun": "SCAR 17S",
  "type": "receiver",
  "image": "assets\\images\\SCAR 17S\\receiver.png",
  "scale": 0.84,
  "attachments": [
    {
      "x": -1,
      "y": -0.6477661513575551,
      "type": "barrel",
      "parent": true
    },
    {
      "x": 0.9444858938474567,
      "y": -0.32766784936154036,
      "type": "stock",
      "parent": true
    },
    {
      "x": -0.00756429225542965,
      "y": -0.6417100382500389,
      "type": "sight",
      "parent": true
    }
  ]
}
